dl_101soundboards/__init__.py
dl_101soundboards/__main__.py
dl_101soundboards/config/__init__.py
dl_101soundboards/config/config.py
dl_101soundboards/config/get_iso639_xxx.py
dl_101soundboards-1.7.0a1.dist-info/LICENSE
dl_101soundboards-1.7.0a1.dist-info/METADATA
dl_101soundboards-1.7.0a1.dist-info/WHEEL
dl_101soundboards-1.7.0a1.dist-info/entry_points.txt
dl_101soundboards-1.7.0a1.dist-info/top_level.txt
dl_101soundboards-1.7.0a1.dist-info/RECORD
