Metadata-Version: 2.2
Name: dl-101soundboards
Version: 1.7.0a1
Summary: Unofficial downloader for www.101soundboards.com
Home-page: https://github.com/gitchasing/dl-101soundboards/
Author: gitchasing
License:                     GNU GENERAL PUBLIC LICENSE
License-File: LICENSE
Requires-Dist: mutagen~=1.47.0
Requires-Dist: pydub~=0.25.1
Requires-Dist: requests~=2.32.3
Requires-Dist: uni-curses~=3.1.2
Dynamic: author
Dynamic: description
Dynamic: home-page
Dynamic: license
Dynamic: requires-dist
Dynamic: summary
